[
  {
    "name": "meadow",
    "trees": [
      {
        "probability": 5,
        "proto": "terrain/models/flora/trees-temperate/poplar-green.glb"
      },
      {
        "probability": 1,
        "proto": "terrain/models/flora/trees-temperate/poplar-green2.glb"
      },
      {
        "probability": 1,
        "proto": "terrain/models/flora/trees-temperate/poplar-orange.glb"
      },
      {
        "probability": 0.5,
        "proto": "terrain/models/flora/trees-temperate/poplar-yellow.glb"
      }
    ],
    "shrubs": [
      {
        "probability": 1,
        "proto": "terrain/models/flora/shrubs/leechgrass.glb"
      }
    ],
    "herbs": [
      {
        "probability": 1,
        "proto": "terrain/models/flora/shrubs/buckberry.glb"
      },
      {
        "probability": 1,
        "proto": "terrain/models/flora/shrubs/eldenthorn.glb"
      },
      {
        "probability": 1,
        "proto": "terrain/models/flora/shrubs/dreamsage.glb"
      },
      {
        "probability": 1,
        "proto": "terrain/models/flora/shrubs/whitespear.glb"
      },
      {
        "probability": 1,
        "proto": "terrain/models/flora/shrubs/wracknettle.glb"
      }
    ],
    "surface": 2
  },
  {
    "name": "underground",
    "trees": [],
    "shrubs": [],
    "herbs": [],
    "surface": 0
  },
  {
    "name": "desert",
    "trees": [
      {
        "probability": 9
      },
      {
        "probability": 1,
        "proto": "terrain/models/flora/trees-desert/desert1.glb"
      }
    ],
    "shrubs": [
      {
        "probability": 3
      },
      {
        "probability": 1,
        "proto": "terrain/models/flora/shrubs/scragbush.glb"
      }
    ],
    "herbs": [
      {
        "probability": 6
      },
      {
        "probability": 2,
        "proto": "terrain/models/flora/shrubs/whitespear.glb"
      },
      {
        "probability": 1,
        "proto": "terrain/models/flora/shrubs/fireweed.glb"
      }
    ],
    "surface": 5
  },
  {
    "name": "arctic",
    "trees": [
      {
        "probability": 2,
        "proto": "terrain/models/flora/trees-arctic/pine.glb-arctic1"
      },
      {
        "probability": 1,
        "proto": "terrain/models/flora/trees-arctic/pine.glb-arctic2"
      },
      {
        "probability": 1,
        "proto": "terrain/models/flora/trees-arctic/pine.glb-arctic3"
      }
    ],
    "shrubs": [
      {
        "probability": 1,
        "proto": "terrain/models/flora/shrubs/scrubthistle.glb"
      },
      {
        "probability": 2,
        "proto": "terrain/models/flora/shrubs/rimeslip.glb"
      }
    ],
    "herbs": [],
    "surface": 7
  },
  {
    "name": "tundra",
    "trees": [
      {
        "probability": 2,
        "proto": "terrain/models/flora/trees-coniferous/pine.glb-fluffy"
      },
      {
        "probability": 2,
        "proto": "terrain/models/flora/trees-coniferous/pine.glb-drooping"
      }
    ],
    "shrubs": [
      {
        "probability": 3,
        "proto": "terrain/models/flora/shrubs/scrubthistle.glb"
      },
      {
        "probability": 1,
        "proto": "terrain/models/flora/shrubs/rimeslip.glb"
      }
    ],
    "herbs": [],
    "surface": 6
  },
  {
    "name": "taiga",
    "trees": [
      {
        "probability": 2,
        "proto": "terrain/models/flora/trees-coniferous/pine.glb-fluffy"
      },
      {
        "probability": 2,
        "proto": "terrain/models/flora/trees-coniferous/pine.glb-drooping"
      }
    ],
    "shrubs": [
      {
        "probability": 1,
        "proto": "terrain/models/flora/shrubs/scrubthistle.glb"
      }
    ],
    "herbs": [],
    "surface": 4
  },
  {
    "name": "barren",
    "trees": [
      {
        "probability": 2,
        "proto": "terrain/models/flora/trees-dead/dead1.glb"
      },
      {
        "probability": 1,
        "proto": "terrain/models/flora/trees-dead/dead2.glb"
      },
      {
        "probability": 1,
        "proto": "terrain/models/flora/trees-dead/dead3.glb"
      },
      {
        "probability": 0.5,
        "proto": "terrain/models/flora/trees-dead/dead4.glb"
      }
    ],
    "shrubs": [
      {
        "probability": 2
      },
      {
        "probability": 1,
        "proto": "terrain/models/flora/shrubs/scragbush.glb"
      }
    ],
    "herbs": [],
    "surface": 1
  },
  {
    "name": "forest",
    "trees": [
      {
        "probability": 2,
        "proto": "terrain/models/flora/trees-temperate/hemlock1.glb"
      },
      {
        "probability": 2,
        "proto": "terrain/models/flora/trees-temperate/hemlock2.glb"
      },
      {
        "probability": 3,
        "proto": "terrain/models/flora/trees-temperate/hemlock3.glb"
      },
      {
        "probability": 3,
        "proto": "terrain/models/flora/trees-temperate/hemlock4.glb"
      }
    ],
    "shrubs": [
      {
        "probability": 1,
        "proto": "terrain/models/flora/shrubs/leechgrass.glb"
      }
    ],
    "herbs": [],
    "surface": 3
  },
  {
    "name": "meadow-light",
    "trees": [
      {
        "probability": 1,
        "proto": "terrain/models/flora/trees-temperate/poplar.glb-ivory"
      },
      {
        "probability": 0.5,
        "proto": "terrain/models/flora/trees-temperate/poplar.glb-green2"
      },
      {
        "probability": 3,
        "proto": "terrain/models/flora/trees-temperate/poplar.glb-orange"
      },
      {
        "probability": 4,
        "proto": "terrain/models/flora/trees-temperate/poplar.glb-yellow"
      }
    ],
    "shrubs": [
      {
        "probability": 1,
        "proto": "terrain/models/flora/shrubs/leechgrass.glb"
      }
    ],
    "herbs": [
      {
        "probability": 1,
        "proto": "terrain/models/flora/shrubs/buckberry.glb"
      },
      {
        "probability": 1,
        "proto": "terrain/models/flora/shrubs/eldenthorn.glb"
      },
      {
        "probability": 1,
        "proto": "terrain/models/flora/shrubs/dreamsage.glb"
      },
      {
        "probability": 1,
        "proto": "terrain/models/flora/shrubs/whitespear.glb"
      },
      {
        "probability": 1,
        "proto": "terrain/models/flora/shrubs/wracknettle.glb"
      }
    ],
    "surface": 2
  },
  {
    "name": "meadow-dark",
    "trees": [
      {
        "probability": 1,
        "proto": "terrain/models/flora/trees-temperate/poplar.glb-green"
      },
      {
        "probability": 0.5,
        "proto": "terrain/models/flora/trees-temperate/poplar.glb-green2"
      },
      {
        "probability": 1,
        "proto": "terrain/models/flora/trees-temperate/poplar.glb-green3"
      },
      {
        "probability": 0.5,
        "proto": "terrain/models/flora/trees-temperate/hemlock1.glb"
      }
    ],
    "shrubs": [
      {
        "probability": 1,
        "proto": "terrain/models/flora/shrubs/leechgrass.glb"
      }
    ],
    "herbs": [
      {
        "probability": 1,
        "proto": "terrain/models/flora/shrubs/buckberry.glb"
      },
      {
        "probability": 1,
        "proto": "terrain/models/flora/shrubs/eldenthorn.glb"
      },
      {
        "probability": 1,
        "proto": "terrain/models/flora/shrubs/dreamsage.glb"
      },
      {
        "probability": 1,
        "proto": "terrain/models/flora/shrubs/whitespear.glb"
      },
      {
        "probability": 1,
        "proto": "terrain/models/flora/shrubs/wracknettle.glb"
      }
    ],
    "surface": 2
  },
  {
    "name": "chaparral",
    "trees": [
      {
        "probability": 1,
        "proto": "terrain/models/flora/trees-temperate/poplar.glb-green"
      },
      {
        "probability": 1,
        "proto": "terrain/models/flora/trees-temperate/poplar.glb-green2"
      },
      {
        "probability": 3,
        "proto": "terrain/models/flora/trees-temperate/poplar.glb-orange"
      },
      {
        "probability": 5,
        "proto": "terrain/models/flora/trees-temperate/poplar.glb-yellow"
      }
    ],
    "shrubs": [
      {
        "probability": 1,
        "proto": "terrain/models/flora/shrubs/sticklebrush.glb"
      }
    ],
    "herbs": [
      {
        "probability": 6
      },
      {
        "probability": 1,
        "proto": "terrain/models/flora/shrubs/eldenthorn.glb"
      },
      {
        "probability": 1,
        "proto": "terrain/models/flora/shrubs/dreamsage.glb"
      },
      {
        "probability": 1,
        "proto": "terrain/models/flora/shrubs/whitespear.glb"
      },
      {
        "probability": 1,
        "proto": "terrain/models/flora/shrubs/wracknettle.glb"
      }
    ],
    "surface": 8
  }
]